agentops/__init__.py
agentops/alert/__init__.py
agentops/alert/registry.py
agentops/core/__init__.py
agentops/core/base_alert.py
agentops/core/base_llm.py
agentops/core/base_parser.py
agentops/core/base_prompt.py
agentops/core/constants.py
agentops/core/types.py
agentops/llm/__init__.py
agentops/llm/openai_llm.py
agentops/llm/registry.py
agentops/parser/__init__.py
agentops/parser/error_parser.py
agentops/parser/registry.py
agentops/prompt/__init__.py
agentops/prompt/jenkins_error_prompt.py
agentops/prompt/registry.py
agentops_sdk-0.1.0.dist-info/LICENSE
agentops_sdk-0.1.0.dist-info/METADATA
agentops_sdk-0.1.0.dist-info/WHEEL
agentops_sdk-0.1.0.dist-info/RECORD
