Metadata-Version: 2.3
Name: agentops-sdk
Version: 0.1.0
Summary: AI-powered failure analysis agent for CI/CD pipelines
License: MIT
Author: Adi Roth
Author-email: adi.build.balance@gmail.com
Requires-Python: >=3.9
Classifier: License :: OSI Approved :: MIT License
Classifier: Programming Language :: Python :: 3
Classifier: Programming Language :: Python :: 3.9
Classifier: Programming Language :: Python :: 3.10
Classifier: Programming Language :: Python :: 3.11
Classifier: Programming Language :: Python :: 3.12
Classifier: Programming Language :: Python :: 3.13
Requires-Dist: coverage (>=7.0.0,<8.0.0)
Requires-Dist: openai (>=1.0.0,<2.0.0)
Requires-Dist: python-dotenv (>=1.0.0,<2.0.0)
